.gitignore
setup.py
graphic_lib/__init__.py
graphic_lib.egg-info/PKG-INFO
graphic_lib.egg-info/SOURCES.txt
graphic_lib.egg-info/dependency_links.txt
graphic_lib.egg-info/not-zip-safe
graphic_lib.egg-info/top_level.txt
graphic_lib/Display/Display.py
graphic_lib/Display/__init__.py
graphic_lib/Font/Font.py
graphic_lib/Font/Glyph.py
graphic_lib/Font/__init__.py
graphic_lib/View/View.py
graphic_lib/View/__init__.py
graphic_lib/detail/Drawable.py
graphic_lib/detail/Widget.py
graphic_lib/detail/__init__.py
graphic_lib/widgets/ColorBox.py
graphic_lib/widgets/TextBox.py
graphic_lib/widgets/__init__.py
tests/Display/__init__.py
tests/Display/test_display.py
tests/Drawable/__init__.py
tests/Drawable/test_Drawable.py
tests/Font/__init__.py
tests/Font/test_Font.py
tests/Font/test_Glyph.py