Metadata-Version: 2.1
Name: graphic-lib
Version: 0.1.0
Summary: Python graphical library
Home-page: https://github.com/ProrokWielki/graphic_lib
Author: Pawel Warzecha
Author-email: pawel.warzecha@yahoo.com
License: MIT
Platform: UNKNOWN
